einsteinpy/__init__.py
einsteinpy/bodies.py
einsteinpy/constant.py
einsteinpy/examples.py
einsteinpy/geodesic.py
einsteinpy/ijit.py
einsteinpy/testing.py
einsteinpy/units.py
einsteinpy/coordinates/__init__.py
einsteinpy/coordinates/conversion.py
einsteinpy/coordinates/core.py
einsteinpy/coordinates/utils.py
einsteinpy/coordinates/velocity.py
einsteinpy/hypersurface/__init__.py
einsteinpy/hypersurface/schwarzschildembedding.py
einsteinpy/integrators/__init__.py
einsteinpy/integrators/runge_kutta.py
einsteinpy/metric/__init__.py
einsteinpy/metric/kerr.py
einsteinpy/metric/kerrnewman.py
einsteinpy/metric/schwarzschild.py
einsteinpy/plotting/__init__.py
einsteinpy/plotting/fractal.py
einsteinpy/plotting/geodesics/__init__.py
einsteinpy/plotting/geodesics/core.py
einsteinpy/plotting/geodesics/interactive.py
einsteinpy/plotting/geodesics/static.py
einsteinpy/plotting/hypersurface/__init__.py
einsteinpy/plotting/hypersurface/core.py
einsteinpy/plotting/rays/__init__.py
einsteinpy/plotting/rays/shadow.py
einsteinpy/rays/__init__.py
einsteinpy/rays/shadow.py
einsteinpy/symbolic/__init__.py
einsteinpy/symbolic/christoffel.py
einsteinpy/symbolic/constants.py
einsteinpy/symbolic/einstein.py
einsteinpy/symbolic/helpers.py
einsteinpy/symbolic/metric.py
einsteinpy/symbolic/ricci.py
einsteinpy/symbolic/riemann.py
einsteinpy/symbolic/schouten.py
einsteinpy/symbolic/stress_energy_momentum.py
einsteinpy/symbolic/tensor.py
einsteinpy/symbolic/vector.py
einsteinpy/symbolic/weyl.py
einsteinpy/symbolic/predefined/__init__.py
einsteinpy/symbolic/predefined/barriola_vilenkin.py
einsteinpy/symbolic/predefined/bertotti_kasner.py
einsteinpy/symbolic/predefined/bessel_gravitational_wave.py
einsteinpy/symbolic/predefined/cmetric.py
einsteinpy/symbolic/predefined/davidson.py
einsteinpy/symbolic/predefined/de_sitter.py
einsteinpy/symbolic/predefined/ernst.py
einsteinpy/symbolic/predefined/find.py
einsteinpy/symbolic/predefined/godel.py
einsteinpy/symbolic/predefined/janis_newman_winicour.py
einsteinpy-0.3.1.dist-info/AUTHORS
einsteinpy-0.3.1.dist-info/COPYING
einsteinpy-0.3.1.dist-info/METADATA
einsteinpy-0.3.1.dist-info/WHEEL
einsteinpy-0.3.1.dist-info/top_level.txt
einsteinpy-0.3.1.dist-info/RECORD
