Metadata-Version: 2.1
Name: einsteinpy
Version: 0.3.1
Summary: Python package for General Relativity
Home-page: https://einsteinpy.org/
Author: Shreyas Bapat
Author-email: bapat.shreyas@gmail.com
License: MIT
Download-URL: https://github.com/einsteinpy/einsteinpy
Keywords: general relativity,geodesics,relativity,kerr,black-hole,kerr-newman,schwarzschild
Platform: UNKNOWN
Classifier: Development Status :: 4 - Beta
Classifier: Intended Audience :: Education
Classifier: Intended Audience :: Science/Research
Classifier: License :: OSI Approved :: MIT License
Classifier: Operating System :: OS Independent
Classifier: Programming Language :: Python
Classifier: Programming Language :: Python :: 3
Classifier: Programming Language :: Python :: 3.6
Classifier: Programming Language :: Python :: 3.7
Classifier: Programming Language :: Python :: 3.8
Classifier: Topic :: Scientific/Engineering
Classifier: Topic :: Scientific/Engineering :: Physics
Classifier: Topic :: Scientific/Engineering :: Astronomy
Requires-Python: >=3.5
Requires-Dist: numpy
Requires-Dist: astropy
Requires-Dist: matplotlib
Requires-Dist: scipy (>=1.0)
Requires-Dist: plotly (>=4.0)
Requires-Dist: sympy (>=1.1)
Requires-Dist: numba (!=0.49.0,>=0.46) ; implementation_name == "cpython"
Provides-Extra: dev
Requires-Dist: coverage ; extra == 'dev'
Requires-Dist: isort ; extra == 'dev'
Requires-Dist: pytest ; extra == 'dev'
Requires-Dist: pytest-xdist ; extra == 'dev'
Requires-Dist: pytest-cov (<2.6.0) ; extra == 'dev'
Requires-Dist: pycodestyle ; extra == 'dev'
Requires-Dist: sphinx ; extra == 'dev'
Requires-Dist: alabaster ; extra == 'dev'
Requires-Dist: nbsphinx ; extra == 'dev'
Requires-Dist: ipython (>=5.0) ; extra == 'dev'
Requires-Dist: jupyter-client ; extra == 'dev'
Requires-Dist: ipykernel ; extra == 'dev'
Requires-Dist: ipywidgets ; extra == 'dev'
Requires-Dist: tox ; extra == 'dev'
Requires-Dist: jupyter-sphinx ; extra == 'dev'
Requires-Dist: black ; (python_version >= "3.6") and extra == 'dev'
